codepeers/__init__.py
codepeers/_version.py
codepeers/handlers.py
codepeers-0.3.3.data/data/etc/jupyter/jupyter_notebook_config.d/codepeers.json
codepeers-0.3.3.data/data/etc/jupyter/jupyter_server_config.d/codepeers.json
codepeers-0.3.3.data/data/share/jupyter/labextensions/codepeers/package.json
codepeers-0.3.3.data/data/share/jupyter/labextensions/codepeers/schemas/codepeers/package.json.orig
codepeers-0.3.3.data/data/share/jupyter/labextensions/codepeers/schemas/codepeers/plugin.json
codepeers-0.3.3.data/data/share/jupyter/labextensions/codepeers/static/1581.3c1a31764373317b85b3.js
codepeers-0.3.3.data/data/share/jupyter/labextensions/codepeers/static/1581.3c1a31764373317b85b3.js.LICENSE.txt
codepeers-0.3.3.data/data/share/jupyter/labextensions/codepeers/static/1739.b30ab9aaa91b5c6ddeba.js
codepeers-0.3.3.data/data/share/jupyter/labextensions/codepeers/static/1779.1358978cd15bd82ae51d.js
codepeers-0.3.3.data/data/share/jupyter/labextensions/codepeers/static/191.d1142ea40af4468bf36f.js
codepeers-0.3.3.data/data/share/jupyter/labextensions/codepeers/static/2002.2ba6d00a60747c2e9c84.js
codepeers-0.3.3.data/data/share/jupyter/labextensions/codepeers/static/2031.60b51eff710521bf9b54.js
codepeers-0.3.3.data/data/share/jupyter/labextensions/codepeers/static/2520.d2cb87c43249401cbac1.js
codepeers-0.3.3.data/data/share/jupyter/labextensions/codepeers/static/2600.4b3028b76f8ed13df8e2.js
codepeers-0.3.3.data/data/share/jupyter/labextensions/codepeers/static/277d94aedda148a9e61d3bc4443ab88214b057d99d49211da2e1e1cca50b8973.png
codepeers-0.3.3.data/data/share/jupyter/labextensions/codepeers/static/2858.9797c6fa72711f45219c.js
codepeers-0.3.3.data/data/share/jupyter/labextensions/codepeers/static/2906.44395555b03b84b63161.js
codepeers-0.3.3.data/data/share/jupyter/labextensions/codepeers/static/3328.a130bfbf5dd7f6553d75.js
codepeers-0.3.3.data/data/share/jupyter/labextensions/codepeers/static/3428.81f932f955342b185407.js
codepeers-0.3.3.dist-info/METADATA
codepeers-0.3.3.dist-info/WHEEL
codepeers-0.3.3.dist-info/licenses/LICENSE
codepeers-0.3.3.dist-info/RECORD
