Metadata-Version: 2.1
Name: codepeers
Version: 0.3.3
Summary: Codepeers JupyterLab extension to review code from your peers.
Project-URL: Homepage, https://github.com/chili-epfl/jupyter-dashboard-for-students
Project-URL: Bug Tracker, https://github.com/chili-epfl/jupyter-dashboard-for-students/issues
Project-URL: Repository, https://github.com/chili-epfl/jupyter-dashboard-for-students.git
Author-email: Everina <me@test.com>
License: BSD 3-Clause License
License-File: LICENSE
Classifier: Framework :: Jupyter
Classifier: Framework :: Jupyter :: JupyterLab
Classifier: Framework :: Jupyter :: JupyterLab :: 3
Classifier: Framework :: Jupyter :: JupyterLab :: Extensions
Classifier: Framework :: Jupyter :: JupyterLab :: Extensions :: Prebuilt
Classifier: License :: OSI Approved :: BSD License
Classifier: Programming Language :: Python
Classifier: Programming Language :: Python :: 3
Classifier: Programming Language :: Python :: 3.7
Classifier: Programming Language :: Python :: 3.8
Classifier: Programming Language :: Python :: 3.9
Classifier: Programming Language :: Python :: 3.10
Classifier: Programming Language :: Python :: 3.11
Requires-Python: >=3.7
Requires-Dist: jupyter-server<3,>=1.21
